plothelp/__init__.py
plothelp/_version.py
plothelp/_version.pyi
plothelp/colours.py
plothelp/plot.py
plothelp/py.typed
plothelp-0.2.dist-info/LICENSE
plothelp-0.2.dist-info/METADATA
plothelp-0.2.dist-info/WHEEL
plothelp-0.2.dist-info/top_level.txt
plothelp-0.2.dist-info/RECORD
