Metadata-Version: 2.1
Name: plothelp
Version: 0.2
Summary: Simple auto-grid pyplot util.
Home-page: https://github.com/phinate/plothelp
Author: Nathan
License: BSD-3-Clause
Project-URL: Documentation, https://plothelp.readthedocs.io/
Project-URL: Bug Tracker, https://github.com/phinate/plothelp/issues
Project-URL: Discussions, https://github.com/phinate/plothelp/discussions
Project-URL: Changelog, https://github.com/phinate/plothelp/releases
Platform: Any
Classifier: Development Status :: 1 - Planning
Classifier: Intended Audience :: Developers
Classifier: Intended Audience :: Science/Research
Classifier: License :: OSI Approved :: BSD License
Classifier: Operating System :: OS Independent
Classifier: Programming Language :: Python
Classifier: Programming Language :: Python :: 3
Classifier: Programming Language :: Python :: 3 :: Only
Classifier: Programming Language :: Python :: 3.7
Classifier: Programming Language :: Python :: 3.8
Classifier: Programming Language :: Python :: 3.9
Classifier: Programming Language :: Python :: 3.10
Classifier: Topic :: Scientific/Engineering
Requires-Python: >=3.7
License-File: LICENSE
Requires-Dist: jax
Requires-Dist: jaxlib
Requires-Dist: matplotlib
Requires-Dist: typing-extensions (>=4.0) ; python_version < "3.8"
Provides-Extra: dev
Requires-Dist: pytest (>=6) ; extra == 'dev'
Provides-Extra: docs
Requires-Dist: Sphinx (>=4.0) ; extra == 'docs'
Requires-Dist: myst-parser (>=0.13) ; extra == 'docs'
Requires-Dist: sphinx-book-theme (>=0.1.0) ; extra == 'docs'
Requires-Dist: sphinx-copybutton ; extra == 'docs'
Provides-Extra: test
Requires-Dist: pytest (>=6) ; extra == 'test'
